blanksort/__init__.py
blanksort/blanksort.py
blanksort/ftooc/__init__.py
blanksort/ftooc/ftooc.py
blanksort-0.0.8.dist-info/LICENSE
blanksort-0.0.8.dist-info/METADATA
blanksort-0.0.8.dist-info/WHEEL
blanksort-0.0.8.dist-info/top_level.txt
blanksort-0.0.8.dist-info/RECORD
