Metadata-Version: 2.1
Name: blanksort
Version: 0.0.8
Summary: The Python package for the BlankSort keyword extraction algorithm.
Home-page: https://github.com/KentoNishi/BlankSort
Author: KentoNishi
Author-email: kento24gs@outlook.com
License: UNKNOWN
Platform: UNKNOWN
Classifier: Programming Language :: Python :: 3
Classifier: License :: Free for non-commercial use
Classifier: Operating System :: OS Independent
Requires-Python: >=3.4
Requires-Dist: nltk (>=3.4.5)
Requires-Dist: numpy (>=1.17.0)
Requires-Dist: sqlitedict (>=1.6.0)
Requires-Dist: requests (>=2.22.0)
